uravu/__init__.py
uravu/_fig_params.py
uravu/axis.py
uravu/distribution.py
uravu/optimize.py
uravu/plotting.py
uravu/relationship.py
uravu/sampling.py
uravu/utils.py
uravu/tests/__init__.py
uravu/tests/test_axis.py
uravu/tests/test_distribution.py
uravu/tests/test_optimize.py
uravu/tests/test_relationship.py
uravu/tests/test_sampling.py
uravu/tests/test_utils.py
uravu-1.3.0.dist-info/LICENSE
uravu-1.3.0.dist-info/METADATA
uravu-1.3.0.dist-info/WHEEL
uravu-1.3.0.dist-info/top_level.txt
uravu-1.3.0.dist-info/RECORD
