Metadata-Version: 2.1
Name: uravu
Version: 1.3.0
Summary: Bayesian methods for analytical relationships
Author: Andrew R. McCluskey
Author-email: andrew.mccluskey@diamond.ac.uk
License: MIT
Classifier: Development Status :: 4 - Beta
Classifier: Intended Audience :: Science/Research
Classifier: License :: OSI Approved :: MIT License
Classifier: Natural Language :: English
Classifier: Operating System :: OS Independent
Classifier: Programming Language :: Python :: 3.6
Classifier: Programming Language :: Python :: 3.7
Classifier: Programming Language :: Python :: 3.8
Classifier: Topic :: Scientific/Engineering
Classifier: Topic :: Scientific/Engineering :: Chemistry
Classifier: Topic :: Scientific/Engineering :: Physics
License-File: LICENSE
Requires-Dist: numpy
Requires-Dist: scipy >=1.5.4
Requires-Dist: emcee
Requires-Dist: tqdm
Requires-Dist: uncertainties
Requires-Dist: dynesty
